{
  "generated_at": "2026-03-17T21:53:00.569137+00:00",
  "site": {
    "channel_username": "InvestmentLaw",
    "channel_title": "СпецИнвестРежимы",
    "site_name": "СпецИнвестРежимы",
    "site_description": "Канал о специальных инвестиционных режимах: льготы, проекты, регулирование и правоприменительная практика.",
    "language": "ru",
    "accent_color": "#91278d",
    "background_color": "#f5f7fa",
    "avatar_path": "assets/channel-avatar.jpg"
  },
  "source": {
    "channel_key": "investment-law",
    "channel_url": "https://t.me/s/InvestmentLaw",
    "comments_enabled": false
  },
  "post": {
    "id": 818,
    "date": "2024-11-01T06:14:13+00:00",
    "text": "​🔸29 октября в рамках XX Всероссийского налогового форума ТПП РФ состоялась сессия «Налоговые льготы для инвесторов»\n \nУчастники обсудили действующие льготы для инвесторов и преференциальные налоговые режимы. \n \nВ обсуждении приняли участие:\n✔️представители ФНС России - заместитель руководителя Службы В.В. Бациев и заместитель начальника Управления налогообложения юридических лиц А.Ю. Коньков;\n✔️ведущий научный сотрудник Центра налоговой политики НИФИ Минфина РФ К.А. Пономарева;\n✔️представители бизнеса.\n\n🔸Модератором круглого стола выступил партнер «Пепеляев Групп» Антон Никифоров. \n\nОн подчеркнул, что возможность применения федерального инвестиционного налогового вычета (ФИНВ), который предусмотрен с 2025 г., окажется доступным лишь ограниченному кругу компаний. Уже сейчас прочтение норм о ФИНВ вызывает ряд вопросов, которые хотелось бы разрешить до вступления льготы в силу.\n\n🔸Сергей Савсерис, старший партнер «Пепеляев Групп», представил тематический обзор судебной практики, обозначив основные проблемы, с которыми сталкиваются инвесторы при использовании налоговых льгот. \n\nСреди них: вопросы отчета срока начала использования инвестором льготы и соответствия инвестора условиям применения той или иной льготы. \n\n🔸Старший партнер «Пепеляев Групп» Рустем Ахметшин остановился на инвестсоглашениях по региональным инвестпроектам. Он на примерах показал, как отсутствие единого рамочного регулирования этой преференции со стороны федерального законодателя затрудняет получение налоговых льгот в отдельных регионах России.\n\n❗️Подробнее об итогах сессии читайте здесь.\n \n#Мероприятия\n \n@InvestmentLaw",
    "text_html": "<a href=\"https://hooks.pro/media/2024/11/01/bot5286148466/file-ZyRxcgf-Un.jpg\" target=\"_blank\" rel=\"noopener noreferrer\">​</a>🔸29 октября в рамках XX Всероссийского налогового форума ТПП РФ состоялась сессия «Налоговые льготы для инвесторов»<br> <br>Участники обсудили действующие льготы для инвесторов и преференциальные налоговые режимы. <br> <br>В обсуждении приняли участие:<br>✔️представители ФНС России - заместитель руководителя Службы В.В. Бациев и заместитель начальника Управления налогообложения юридических лиц А.Ю. Коньков;<br>✔️ведущий научный сотрудник Центра налоговой политики НИФИ Минфина РФ К.А. Пономарева;<br>✔️представители бизнеса.<br><br>🔸Модератором круглого стола выступил партнер «Пепеляев Групп» Антон Никифоров. <br><br>Он подчеркнул, что возможность применения федерального инвестиционного налогового вычета (ФИНВ), который предусмотрен с 2025 г., окажется доступным лишь ограниченному кругу компаний. Уже сейчас прочтение норм о ФИНВ вызывает ряд вопросов, которые хотелось бы разрешить до вступления льготы в силу.<br><br>🔸Сергей Савсерис, старший партнер «Пепеляев Групп», представил тематический обзор судебной практики, обозначив основные проблемы, с которыми сталкиваются инвесторы при использовании налоговых льгот. <br><br>Среди них: вопросы отчета срока начала использования инвестором льготы и соответствия инвестора условиям применения той или иной льготы. <br><br>🔸Старший партнер «Пепеляев Групп» Рустем Ахметшин остановился на инвестсоглашениях по региональным инвестпроектам. Он на примерах показал, как отсутствие единого рамочного регулирования этой преференции со стороны федерального законодателя затрудняет получение налоговых льгот в отдельных регионах России.<br><br>❗️Подробнее об итогах сессии <a href=\"https://nalogoved.ru/news/14876.html\" target=\"_blank\" rel=\"noopener noreferrer\">читайте здесь</a><a href=\"https://nalogoved.ru/news/14876.html\" target=\"_blank\" rel=\"noopener noreferrer\">.</a><br> <br>#Мероприятия<br> <br><a href=\"https://t.me/InvestmentLaw\" target=\"_blank\" rel=\"noopener noreferrer\">@InvestmentLaw</a>",
    "views": 346,
    "comments_count": 0,
    "comments_url": null,
    "photos": [
      {
        "thumb_url": "data/channels/investment-law/media/posts/thumbs/818-1-fa1e55a74810-v2.jpg",
        "full_url": "data/channels/investment-law/media/posts/818-1-fa1e55a74810-v2.jpg"
      }
    ],
    "video_url": null,
    "tg_url": "https://t.me/InvestmentLaw/818",
    "permalink": "channels/investment-law/posts/818/"
  }
}
