{
  "generated_at": "2026-03-17T21:58:14.410074+00:00",
  "site": {
    "channel_username": "bankrotstvo_mustknow",
    "channel_title": "Банкротство | Взгляд эксперта",
    "site_name": "Банкротство | Взгляд эксперта",
    "site_description": "Канал о банкротстве и реструктуризации: обзоры практики, комментарии экспертов и важные кейсы.",
    "language": "ru",
    "accent_color": "#91278d",
    "background_color": "#f5f7fa",
    "avatar_path": "assets/channel-avatar.jpg"
  },
  "source": {
    "channel_key": "bankrotstvo-mustknow",
    "channel_url": "https://t.me/s/bankrotstvo_mustknow",
    "comments_enabled": false
  },
  "post": {
    "id": 184,
    "date": "2025-06-09T08:02:04+00:00",
    "text": "🎯 Быть или не быть банкротству Санатория - вот в чем вопрос! \n \nЮлия Литовцева, партнер, руководитель практики банкротства и антикризисной защиты бизнеса, комментирует интересное Определение ВС РФ о передаче спора для рассмотрения в СКЭС ВС РФ 👇 \n\nКредитор обратился в суд с заявлением о признании Санатория банкротом.\n \nОднако суды все никак не могли прийти к единогласному мнению при разрешении спора:\n \n1⃣⚖  Первая инстанция во введении процедуры наблюдения в отношении Санатория отказала и прекратила производство\nпо делу ввиду погашения третьим лицом основного долга перед Кредитором по правилам ст. 313 ГК РФ.\n2⃣⚖  Апелляция судебный акт отменила и направила вопрос о возможности прекращения производства на новое рассмотрение, т.к. Санаторий не погашал долг длительное время, вплоть до\nвозбуждения дела о банкротстве, поэтому суду первой инстанции следовало проверить доводы Кредитора об отсутствии у Санатория в настоящее время активов, достаточных для исполнения обязательств перед кредиторами в полном объеме.\n3⃣⚖  Кассация с апелляцией не согласилась и оставила в силе судебный акт первой инстанции.\n \nОднако ВС РФ счел заслуживающими внимания доводы Кредитора и передал спор на рассмотрение СКЭС ВС РФ, т. к.:\n \n📌 ранее в отношении Санатория уже возбуждалось дело о банкротстве, которое было прекращено в связи с погашением третьим лицом требований кредиторов, включенных в реестр;\n📌 в результате непогашенными остались текущие требования, однако когда правопреемник по этим требованиям обратился с иском к Санаторию, последний изменил свой адрес и зарегистрировался в другом регионе; указанный иск судом был удовлетворен;\n📌 после прекращения первого дела о банкротстве Санаторий произвел отчуждение всего принадлежащего ему имущества, одному из покупателей – в отсутствие встречного исполнения по оплате (Покупатель);\n📌 после возбуждения производства по второму делу о банкротстве Кредитором горе-Покупатель погасил за Санаторий только сумму основного долга, проигнорировав неустойку;\n📌 указанные действия Покупателя апелляционный суд также посчитал подозрительнымии направленными исключительно на создание формальных препятствий к оспариванию подозрительных сделок Санатория по отчуждению практически всегонедвижимого имущества в ущерб Кредитору.\n \n❗ В числе лиц, наиболее часто злоупотребляющих правами в делах о банкротстве, должники находятся на лидирующей позиции!\n\n💬 \"Комментируемое дело – кладезь форм и способов недобросовестного поведения должника и органов его управления, что очевидно и привело к признанию судьей ВС кассационной жалобы приемлемой. Неисполнение обязательств перед кредиторами при наличии активов; вывод имущества; банкротный туризм; принятие исполнения от третьего лица при одновременном неинициировании банкротства – неполный перечень того, что имело место. Судья ВС РФ отметил еще одну форму злоупотреблений, но уже со стороны приобретателя активов: неисполнение обязательств по оплате приобретенных активов. Не исключено, что обстоятельства, связанные со сделкой, могут быть оценены как подтверждающие фактическую аффилированность покупателя. На это наталкивают сам факт совершения сделки вскоре после прекращения первого банкротства; длительное неистребование должником оплаты; заключение мирового соглашения с продлением срока оплаты.\" - отмечает Ю. Литовцева.\n\nИсточник: PROбанкротство\n\n#Мнение_юриста\n#Требования_кредиторов",
    "text_html": "🎯 Быть или не быть банкротству Санатория - вот в чем вопрос! <br> <br>Юлия Литовцева, партнер, руководитель <a href=\"https://www.pgplaw.ru/practice-and-industry/practices/bankruptcy/\" target=\"_blank\" rel=\"noopener noreferrer\">практики банкротства и антикризисной защиты бизнеса,</a> комментирует интересное <a href=\"https://ras.arbitr.ru/Document/Pdf/d7751da8-6187-4ead-8ec6-1c96b508079e/8ad5811b-040f-4a2a-a6b9-5c02825b155c/%D0%9032-57879-2023__20250529.pdf?isAddStamp=True\" target=\"_blank\" rel=\"noopener noreferrer\">Определение ВС РФ о передаче спора для рассмотрения в СКЭС ВС РФ</a> 👇 <br><br>Кредитор обратился в суд с заявлением о признании Санатория банкротом.<br> <br>Однако суды все никак не могли прийти к единогласному мнению при разрешении спора:<br> <br>1⃣⚖  Первая инстанция во введении процедуры наблюдения в отношении Санатория отказала и прекратила производство<br>по делу ввиду погашения третьим лицом основного долга перед Кредитором по правилам ст. 313 ГК РФ.<br>2⃣⚖  Апелляция судебный акт отменила и направила вопрос о возможности прекращения производства на новое рассмотрение, т.к. Санаторий не погашал долг длительное время, вплоть до<br>возбуждения дела о банкротстве, поэтому суду первой инстанции следовало проверить доводы Кредитора об отсутствии у Санатория в настоящее время активов, достаточных для исполнения обязательств перед кредиторами в полном объеме.<br>3⃣⚖  Кассация с апелляцией не согласилась и оставила в силе судебный акт первой инстанции.<br> <br>Однако ВС РФ счел заслуживающими внимания доводы Кредитора и передал спор на рассмотрение СКЭС ВС РФ, т. к.:<br> <br>📌 ранее в отношении Санатория уже возбуждалось дело о банкротстве, которое было прекращено в связи с погашением третьим лицом требований кредиторов, включенных в реестр;<br>📌 в результате непогашенными остались текущие требования, однако когда правопреемник по этим требованиям обратился с иском к Санаторию, последний изменил свой адрес и зарегистрировался в другом регионе; указанный иск судом был удовлетворен;<br>📌 после прекращения первого дела о банкротстве Санаторий произвел отчуждение всего принадлежащего ему имущества, одному из покупателей – в отсутствие встречного исполнения по оплате (Покупатель);<br>📌 после возбуждения производства по второму делу о банкротстве Кредитором горе-Покупатель погасил за Санаторий только сумму основного долга, проигнорировав неустойку;<br>📌 указанные действия Покупателя апелляционный суд также посчитал подозрительнымии направленными исключительно на создание формальных препятствий к оспариванию подозрительных сделок Санатория по отчуждению практически всегонедвижимого имущества в ущерб Кредитору.<br> <br>❗ В числе лиц, наиболее часто злоупотребляющих правами в делах о банкротстве, должники находятся на лидирующей позиции!<br><br>💬 \"Комментируемое дело – кладезь форм и способов недобросовестного поведения должника и органов его управления, что очевидно и привело к признанию судьей ВС кассационной жалобы приемлемой. Неисполнение обязательств перед кредиторами при наличии активов; вывод имущества; банкротный туризм; принятие исполнения от третьего лица при одновременном неинициировании банкротства – неполный перечень того, что имело место. Судья ВС РФ отметил еще одну форму злоупотреблений, но уже со стороны приобретателя активов: неисполнение обязательств по оплате приобретенных активов. Не исключено, что обстоятельства, связанные со сделкой, могут быть оценены как подтверждающие фактическую аффилированность покупателя. На это наталкивают сам факт совершения сделки вскоре после прекращения первого банкротства; длительное неистребование должником оплаты; заключение мирового соглашения с продлением срока оплаты.\" - отмечает Ю. Литовцева.<br><br>Источник: <a href=\"https://probankrotstvo.ru/news/vs-razieiasnit-podxod-k-prekrashheniiu-del-o-bankrotstve-pri-casticnom-pogasenii-dolga-8723\" target=\"_blank\" rel=\"noopener noreferrer\">PROбанкротство</a><br><br>#Мнение_юриста<br>#Требования_кредиторов",
    "views": 483,
    "comments_count": 0,
    "comments_url": null,
    "photos": [
      {
        "thumb_url": "data/channels/bankrotstvo-mustknow/media/posts/thumbs/184-1-58745f19a9eb-v2.jpg",
        "full_url": "data/channels/bankrotstvo-mustknow/media/posts/184-1-58745f19a9eb-v2.jpg"
      }
    ],
    "video_url": null,
    "tg_url": "https://t.me/bankrotstvo_mustknow/184",
    "permalink": "channels/bankrotstvo-mustknow/posts/184/"
  }
}
