{
  "generated_at": "2026-04-13T16:47:49.519Z",
  "exit_code": 1,
  "commit_sha": "a6a14ae863dc833925b97f8d9faab3e87373150a",
  "run_id": "24355114643",
  "tail": [
    "2026-04-13 16:41:26,407 INFO Using prefetched channel page https://t.me/s/PgAntitrust",
    "2026-04-13 16:41:27,425 INFO Fetching https://t.me/s/PgAntitrust?before=1367",
    "2026-04-13 16:41:29,464 INFO Fetching https://t.me/s/PgAntitrust?before=1339",
    "2026-04-13 16:41:30,441 INFO Collected 39 posts from the last 3 months",
    "2026-04-13 16:41:30,442 WARNING Latest collected post for @PgAntitrust did not advance beyond 1386. Probing direct Telegram post pages.",
    "2026-04-13 16:41:38,401 INFO Recovered 2 missing gap posts via direct Telegram pages: 1369, 1368",
    "2026-04-13 16:41:38,402 WARNING Deduplicated 2 repeated post entries for @PgAntitrust before media sync",
    "2026-04-13 16:41:38,402 INFO Enriching 4 forwarded posts from forwarded source pages",
    "2026-04-13 16:41:56,117 INFO Telegram user session is not configured. Reply reference sync skipped.",
    "2026-04-13 16:41:56,117 INFO Telegram user session is not configured. High-resolution media refresh skipped.",
    "2026-04-13 16:41:56,117 INFO Telegram user session is not configured. Video media sync skipped.",
    "2026-04-13 16:41:56,117 INFO Telegram user session is not configured. Comment sync skipped.",
    "2026-04-13 16:42:06,373 WARNING Failed to fetch link preview page for post 1360: <urlopen error timed out>",
    "2026-04-13 16:42:07,596 WARNING Failed to fetch link preview page for post 1359: HTTP Error 401: Unauthorized",
    "2026-04-13 16:42:08,576 INFO Updated docs/data/channels/pg-antitrust/posts.json",
    "2026-04-13 16:42:08,578 INFO Updated docs/data/channels/pg-antitrust/pages/2.json",
    "2026-04-13 16:42:08,579 INFO No material changes in docs/data/channels/pg-antitrust/pages/3.json",
    "2026-04-13 16:42:08,579 INFO Done. Material changes detected: yes",
    "Archive stats for pg-antitrust: total 216.2 MB (+0.0 MB), media 215.9 MB (+0.0 MB), pages 2",
    "[main 0d6ec73] chore: refresh telegram mirror (pg-antitrust) [skip ci]",
    " 2 files changed, 23 insertions(+), 23 deletions(-)",
    "From https://github.com/pgplaw/pgp_official",
    " * branch            main       -> FETCH_HEAD",
    "Current branch main is up to date.",
    "To https://github.com/pgplaw/pgp_official",
    "   4009d8f..0d6ec73  main -> main",
    "=== Progressive publish for pg-tax ===",
    "=== Syncing PG Tax | Налоги (@PG_Tax) ===",
    "2026-04-13 16:42:11,927 INFO Using prefetched channel page https://t.me/s/PG_Tax",
    "2026-04-13 16:42:12,956 INFO Fetching https://t.me/s/PG_Tax?before=2570",
    "2026-04-13 16:42:15,116 INFO Fetching https://t.me/s/PG_Tax?before=2549",
    "2026-04-13 16:42:17,232 INFO Fetching https://t.me/s/PG_Tax?before=2529",
    "2026-04-13 16:42:19,369 INFO Fetching https://t.me/s/PG_Tax?before=2509",
    "2026-04-13 16:42:21,423 INFO Fetching https://t.me/s/PG_Tax?before=2485",
    "2026-04-13 16:42:23,514 INFO Fetching https://t.me/s/PG_Tax?before=2464",
    "2026-04-13 16:42:25,535 INFO Fetching https://t.me/s/PG_Tax?before=2444",
    "2026-04-13 16:42:27,617 INFO Fetching https://t.me/s/PG_Tax?before=2424",
    "2026-04-13 16:42:29,718 INFO Fetching https://t.me/s/PG_Tax?before=2403",
    "2026-04-13 16:42:30,675 INFO Collected 180 posts from the last 3 months",
    "2026-04-13 16:42:30,676 WARNING Latest collected post for @PG_Tax did not advance beyond 2589. Probing direct Telegram post pages.",
    "2026-04-13 16:42:35,877 INFO Enriching 9 reply posts from Telegram post pages",
    "2026-04-13 16:42:40,512 INFO Enriching 10 forwarded posts from forwarded source pages",
    "2026-04-13 16:43:26,839 INFO Resolving 5 reply references from Telegram web pages",
    "2026-04-13 16:43:40,091 INFO Telegram user session is not configured. High-resolution media refresh skipped.",
    "2026-04-13 16:43:40,091 INFO Telegram user session is not configured. Video media sync skipped.",
    "2026-04-13 16:43:40,091 INFO Telegram user session is not configured. Comment sync skipped.",
    "2026-04-13 16:43:58,197 WARNING Failed to fetch link preview page for post 2585: HTTP Error 302: The HTTP server returned a redirect error that would lead to an infinite loop.",
    "The last 30x error message was:",
    "Found",
    "2026-04-13 16:44:06,935 WARNING Failed to fetch link preview page for post 2522: <urlopen error timed out>",
    "2026-04-13 16:44:10,785 WARNING Failed to fetch link preview page for post 2431: HTTP Error 404: Not Found",
    "2026-04-13 16:44:21,955 WARNING Failed to fetch link preview page for post 2420: HTTP Error 302: The HTTP server returned a redirect error that would lead to an infinite loop.",
    "The last 30x error message was:",
    "Found",
    "2026-04-13 16:44:22,440 INFO Updated docs/data/channels/pg-tax/posts.json",
    "2026-04-13 16:44:22,443 INFO Updated docs/data/channels/pg-tax/pages/2.json",
    "2026-04-13 16:44:22,446 INFO Updated docs/data/channels/pg-tax/pages/3.json",
    "2026-04-13 16:44:22,447 INFO No material changes in docs/data/channels/pg-tax/pages/4.json",
    "2026-04-13 16:44:22,449 INFO Updated docs/data/channels/pg-tax/pages/5.json",
    "2026-04-13 16:44:22,451 INFO Updated docs/data/channels/pg-tax/pages/6.json",
    "2026-04-13 16:44:22,454 INFO Updated docs/data/channels/pg-tax/pages/7.json",
    "2026-04-13 16:44:22,456 INFO Updated docs/data/channels/pg-tax/pages/8.json",
    "2026-04-13 16:44:22,457 INFO No material changes in docs/data/channels/pg-tax/pages/9.json",
    "2026-04-13 16:44:22,458 INFO No material changes in docs/data/channels/pg-tax/pages/10.json",
    "2026-04-13 16:44:22,459 INFO No material changes in docs/data/channels/pg-tax/pages/11.json",
    "2026-04-13 16:44:22,460 INFO No material changes in docs/data/channels/pg-tax/pages/12.json",
    "2026-04-13 16:44:22,460 INFO Done. Material changes detected: yes",
    "Archive stats for pg-tax: total 1376.8 MB (+0.1 MB), media 1375.5 MB (+0.1 MB), pages 11",
    "[main 0151a55] chore: refresh telegram mirror (pg-tax) [skip ci]",
    " 9 files changed, 53 insertions(+), 53 deletions(-)",
    " create mode 100644 docs/data/channels/pg-tax/media/posts/video-posters/2449-video-note-poster-60c35279eb01-v1.jpg",
    " create mode 100644 docs/data/channels/pg-tax/media/posts/video-posters/2584-video-note-poster-43b6820fa099-v1.jpg",
    "From https://github.com/pgplaw/pgp_official",
    " * branch            main       -> FETCH_HEAD",
    "Current branch main is up to date.",
    "To https://github.com/pgplaw/pgp_official",
    "   0d6ec73..0151a55  main -> main",
    "=== Progressive publish for pg-real-estate ===",
    "=== Syncing PG Real Estate | Недвижимость (@PG_RealEstate) ===",
    "2026-04-13 16:44:25,945 INFO Using prefetched channel page https://t.me/s/PG_RealEstate",
    "2026-04-13 16:44:26,967 INFO Fetching https://t.me/s/PG_RealEstate?before=211",
    "2026-04-13 16:44:28,079 INFO Collected 24 posts from the last 3 months",
    "2026-04-13 16:44:28,080 WARNING Latest collected post for @PG_RealEstate did not advance beyond 232. Probing direct Telegram post pages.",
    "2026-04-13 16:44:38,519 INFO Recovered 3 missing gap posts via direct Telegram pages: 228, 227, 217",
    "2026-04-13 16:44:38,520 WARNING Deduplicated 2 repeated post entries for @PG_RealEstate before media sync",
    "2026-04-13 16:44:38,520 INFO Enriching 8 forwarded posts from forwarded source pages",
    "2026-04-13 16:45:16,485 INFO Telegram user session is not configured. Reply reference sync skipped.",
    "2026-04-13 16:45:16,485 INFO Telegram user session is not configured. High-resolution media refresh skipped.",
    "2026-04-13 16:45:16,485 INFO Telegram user session is not configured. Video media sync skipped.",
    "2026-04-13 16:45:16,486 INFO Telegram user session is not configured. Comment sync skipped.",
    "2026-04-13 16:45:23,566 WARNING Failed to fetch link preview page for post 230: <urlopen error timed out>",
    "2026-04-13 16:45:30,328 INFO Updated docs/data/channels/pg-real-estate/posts.json",
    "2026-04-13 16:45:30,329 INFO No material changes in docs/data/channels/pg-real-estate/pages/2.json",
    "2026-04-13 16:45:30,329 INFO Done. Material changes detected: yes",
    "Archive stats for pg-real-estate: total 79.4 MB (+0.0 MB), media 79.2 MB (+0.0 MB), pages 1",
    "[main 0fab027] chore: refresh telegram mirror (pg-real-estate) [skip ci]",
    " 1 file changed, 5 insertions(+), 5 deletions(-)",
    "From https://github.com/pgplaw/pgp_official",
    " * branch            main       -> FETCH_HEAD",
    "Current branch main is up to date.",
    "To https://github.com/pgplaw/pgp_official",
    "   0151a55..0fab027  main -> main",
    "=== Progressive publish for investment-law ===",
    "=== Syncing СпецИнвестРежимы (@InvestmentLaw) ===",
    "2026-04-13 16:45:33,672 INFO Using prefetched channel page https://t.me/s/InvestmentLaw",
    "2026-04-13 16:45:34,694 INFO Fetching https://t.me/s/InvestmentLaw?before=1059",
    "2026-04-13 16:45:36,887 INFO Fetching https://t.me/s/InvestmentLaw?before=1033",
    "2026-04-13 16:45:37,939 INFO Collected 43 posts from the last 3 months",
    "2026-04-13 16:45:37,939 WARNING Latest collected post for @InvestmentLaw did not advance beyond 1084. Probing direct Telegram post pages.",
    "Traceback (most recent call last):",
    "  File \"/home/runner/work/pgp_official/pgp_official/scripts/sync_channel.py\", line 5383, in <module>",
    "    sys.exit(main())",
    "             ^^^^^^",
    "  File \"/home/runner/work/pgp_official/pgp_official/scripts/sync_channel.py\", line 5261, in main",
    "    posts = probe_newer_posts_from_direct_pages(",
    "            ^^^^^^^^^^^^^^^^^^^^^^^^^^^^^^^^^^^^",
    "  File \"/home/runner/work/pgp_official/pgp_official/scripts/sync_channel.py\", line 3408, in probe_newer_posts_from_direct_pages",
    "    raise RuntimeError(",
    "RuntimeError: Direct probe for @InvestmentLaw did not recover newer posts after the top post regressed from 1084 to 1083 (stale candidates: n/a; hard_errors=0)",
    "Archive stats for investment-law: total 336.9 MB (+0.0 MB), media 336.5 MB (+0.0 MB), pages 2",
    "=== Progressive publish for pg-ecology ===",
    "=== Syncing PG Ecology | Экология (@pgecology) ===",
    "2026-04-13 16:45:44,906 INFO Using prefetched channel page https://t.me/s/pgecology",
    "2026-04-13 16:45:45,927 INFO Fetching https://t.me/s/pgecology?before=1302",
    "2026-04-13 16:45:47,916 INFO Fetching https://t.me/s/pgecology?before=1280",
    "2026-04-13 16:45:48,923 INFO Collected 48 posts from the last 3 months",
    "2026-04-13 16:45:48,924 WARNING Latest collected post for @pgecology did not advance beyond 1321. Probing direct Telegram post pages.",
    "2026-04-13 16:45:56,870 INFO Recovered 2 missing gap posts via direct Telegram pages: 1309, 1308",
    "2026-04-13 16:45:56,872 WARNING Deduplicated 2 repeated post entries for @pgecology before media sync",
    "2026-04-13 16:45:56,872 INFO Enriching 1 forwarded posts from forwarded source pages",
    "2026-04-13 16:46:01,144 INFO Telegram user session is not configured. Reply reference sync skipped.",
    "2026-04-13 16:46:01,145 INFO Telegram user session is not configured. High-resolution media refresh skipped.",
    "2026-04-13 16:46:01,145 INFO Telegram user session is not configured. Video media sync skipped.",
    "2026-04-13 16:46:01,145 INFO Telegram user session is not configured. Comment sync skipped.",
    "2026-04-13 16:46:04,476 INFO Updated docs/data/channels/pg-ecology/posts.json",
    "2026-04-13 16:46:04,478 INFO Updated docs/data/channels/pg-ecology/pages/2.json",
    "2026-04-13 16:46:04,480 INFO Updated docs/data/channels/pg-ecology/pages/3.json",
    "2026-04-13 16:46:04,480 INFO Done. Material changes detected: yes",
    "Archive stats for pg-ecology: total 151.0 MB (+0.0 MB), media 150.8 MB (+0.0 MB), pages 2",
    "[main 919a1ae] chore: refresh telegram mirror (pg-ecology) [skip ci]",
    " 3 files changed, 17 insertions(+), 17 deletions(-)",
    "From https://github.com/pgplaw/pgp_official",
    " * branch            main       -> FETCH_HEAD",
    "Current branch main is up to date.",
    "To https://github.com/pgplaw/pgp_official",
    "   0fab027..919a1ae  main -> main",
    "=== Progressive publish for bankrotstvo-mustknow ===",
    "=== Syncing Банкротство | Взгляд эксперта (@bankrotstvo_mustknow) ===",
    "2026-04-13 16:46:08,034 INFO Using prefetched channel page https://t.me/s/bankrotstvo_mustknow",
    "2026-04-13 16:46:09,059 INFO Fetching https://t.me/s/bankrotstvo_mustknow?before=442",
    "2026-04-13 16:46:11,156 INFO Fetching https://t.me/s/bankrotstvo_mustknow?before=417",
    "2026-04-13 16:46:13,326 INFO Fetching https://t.me/s/bankrotstvo_mustknow?before=397",
    "2026-04-13 16:46:14,468 INFO Collected 76 posts from the last 3 months",
    "2026-04-13 16:46:14,468 WARNING Latest collected post for @bankrotstvo_mustknow did not advance beyond 466. Probing direct Telegram post pages.",
    "2026-04-13 16:46:27,767 INFO Recovered 2 missing gap posts via direct Telegram pages: 441, 440",
    "2026-04-13 16:46:27,769 WARNING Deduplicated 2 repeated post entries for @bankrotstvo_mustknow before media sync",
    "2026-04-13 16:46:27,769 INFO Enriching 5 forwarded posts from forwarded source pages",
    "2026-04-13 16:46:51,470 INFO Telegram user session is not configured. Reply reference sync skipped.",
    "2026-04-13 16:46:51,471 INFO Telegram user session is not configured. High-resolution media refresh skipped.",
    "2026-04-13 16:46:51,471 INFO Telegram user session is not configured. Video media sync skipped.",
    "2026-04-13 16:46:51,471 INFO Telegram user session is not configured. Comment sync skipped.",
    "2026-04-13 16:47:10,592 INFO Updated docs/data/channels/bankrotstvo-mustknow/posts.json",
    "2026-04-13 16:47:10,594 INFO Updated docs/data/channels/bankrotstvo-mustknow/pages/2.json",
    "2026-04-13 16:47:10,597 INFO Updated docs/data/channels/bankrotstvo-mustknow/pages/3.json",
    "2026-04-13 16:47:10,599 INFO Updated docs/data/channels/bankrotstvo-mustknow/pages/4.json",
    "2026-04-13 16:47:10,601 INFO Updated docs/data/channels/bankrotstvo-mustknow/pages/5.json",
    "2026-04-13 16:47:10,601 INFO Done. Material changes detected: yes",
    "Archive stats for bankrotstvo-mustknow: total 526.1 MB (+0.0 MB), media 525.6 MB (+0.0 MB), pages 4",
    "[main 15b2ebe] chore: refresh telegram mirror (bankrotstvo-mustknow) [skip ci]",
    " 5 files changed, 38 insertions(+), 38 deletions(-)",
    "From https://github.com/pgplaw/pgp_official",
    " * branch            main       -> FETCH_HEAD",
    "Current branch main is up to date.",
    "To https://github.com/pgplaw/pgp_official",
    "   919a1ae..15b2ebe  main -> main",
    "=== Progressive publish for pg-employment ===",
    "=== Syncing PG Employment | Трудовое право (@pgEmployment) ===",
    "2026-04-13 16:47:13,913 INFO Using prefetched channel page https://t.me/s/pgEmployment",
    "2026-04-13 16:47:14,937 INFO Fetching https://t.me/s/pgEmployment?before=1945",
    "2026-04-13 16:47:15,966 INFO Collected 37 posts from the last 3 months",
    "2026-04-13 16:47:22,254 INFO Recovered 2 missing gap posts via direct Telegram pages: 1955, 1954",
    "2026-04-13 16:47:22,255 WARNING Deduplicated 2 repeated post entries for @pgEmployment before media sync",
    "2026-04-13 16:47:22,255 INFO Enriching 3 forwarded posts from forwarded source pages",
    "2026-04-13 16:47:36,032 INFO Telegram user session is not configured. High-resolution media refresh skipped.",
    "2026-04-13 16:47:36,032 INFO Telegram user session is not configured. Video media sync skipped.",
    "2026-04-13 16:47:36,033 INFO Telegram user session is not configured. Comment sync skipped.",
    "2026-04-13 16:47:47,933 WARNING Failed to fetch link preview page for post 1949: <urlopen error timed out>",
    "2026-04-13 16:47:47,934 WARNING Failed to fetch link preview page for post 1938: 'latin-1' codec can't encode characters in position 0-14: ordinal not in range(256)",
    "2026-04-13 16:47:48,033 INFO Updated docs/data/channels/pg-employment/posts.json",
    "2026-04-13 16:47:48,035 INFO Updated docs/data/channels/pg-employment/pages/2.json",
    "2026-04-13 16:47:48,036 INFO Updated docs/data/channels/pg-employment/pages/3.json",
    "2026-04-13 16:47:48,036 INFO Done. Material changes detected: yes",
    "Archive stats for pg-employment: total 45.1 MB (+0.0 MB), media 44.8 MB (+0.0 MB), pages 2",
    "[main b29e1a4] chore: refresh telegram mirror (pg-employment) [skip ci]",
    " 3 files changed, 70 insertions(+), 70 deletions(-)",
    "From https://github.com/pgplaw/pgp_official",
    " * branch            main       -> FETCH_HEAD",
    "Current branch main is up to date.",
    "To https://github.com/pgplaw/pgp_official",
    "   15b2ebe..b29e1a4  main -> main"
  ]
}
