{
  "generated_at": "2026-03-17T21:55:05.939941+00:00",
  "site": {
    "channel_username": "pgecology",
    "channel_title": "PG Ecology | Экология",
    "site_name": "PG Ecology | Экология",
    "site_description": "Канал экологической практики «Пепеляев Групп»: требования, надзор, комплаенс и ключевые изменения регулирования.",
    "language": "ru",
    "accent_color": "#91278d",
    "background_color": "#f5f7fa",
    "avatar_path": "assets/channel-avatar.jpg"
  },
  "source": {
    "channel_key": "pg-ecology",
    "channel_url": "https://t.me/s/pgecology",
    "comments_enabled": false
  },
  "post": {
    "id": 1251,
    "date": "2025-12-05T04:00:12+00:00",
    "text": "#РешаемСпор\n\n⚔️ Теруправление Росрыболовства взыскивает вред водным биоресурсам с 🛡Предприятия в результате разлива отходов животноводства (свиной навоз) на рельеф местности.\nФакт и размер вреда Истец обосновал материалами уголовного дела в отношении бывшего директора, прекращенного по нереабилитирующим основаниям.\n\nОтветчик возразил об отсутствии причинно-следственной связи его деятельности с наступившим вредом, а также о существенном антропогенном воздействии на реку иными производственными объектами и СНТ.\n\n А как считаете Вы\n\n1️⃣ Для привлечения к имущественной ответственности обязательным является установление причинно-следственной связи производственной деятельности Ответчика и загрязнением водного объекта, в т.ч. с учетом состава загрязняющих веществ.\n\n2️⃣ Достаточно представления доказательств, подтверждающих с разумной степенью вероятности, что загрязнение окружающей среды связано, прежде всего, с хозяйственной деятельностью ответчика.",
    "text_html": "#РешаемСпор<br><br>⚔️ Теруправление Росрыболовства взыскивает вред водным биоресурсам с 🛡Предприятия в результате разлива отходов животноводства (свиной навоз) на рельеф местности.<br>Факт и размер вреда Истец обосновал материалами уголовного дела в отношении бывшего директора, прекращенного по нереабилитирующим основаниям.<br><br>Ответчик возразил об отсутствии причинно-следственной связи его деятельности с наступившим вредом, а также о существенном антропогенном воздействии на реку иными производственными объектами и СНТ.<br><br> А как считаете Вы<br><br>1️⃣ Для привлечения к имущественной ответственности обязательным является установление причинно-следственной связи производственной деятельности Ответчика и загрязнением водного объекта, в т.ч. с учетом состава загрязняющих веществ.<br><br>2️⃣ Достаточно представления доказательств, подтверждающих с разумной степенью вероятности, что загрязнение окружающей среды связано, прежде всего, с хозяйственной деятельностью ответчика.",
    "views": 769,
    "comments_count": 0,
    "comments_url": null,
    "photos": [
      {
        "thumb_url": "data/channels/pg-ecology/media/posts/thumbs/1251-1-aa5f5f3dd420-v2.jpg",
        "full_url": "data/channels/pg-ecology/media/posts/1251-1-aa5f5f3dd420-v2.jpg"
      }
    ],
    "video_url": null,
    "tg_url": "https://t.me/pgecology/1251",
    "permalink": "channels/pg-ecology/posts/1251/"
  }
}
